var point = {"type":"FeatureCollection","features":[{"type":"Feature","properties":{"marker-color":"#ff8000","marker-size":"medium","marker-symbol":"college","Name":"Liverpool University"},"geometry":{"type":"Point","coordinates":[-2.9641199111938477,53.40198465185841]}},{"type":"Feature","properties":{"marker-color":"#ff8000","marker-size":"medium","marker-symbol":"college","Name":"Liverpool John Moores University"},"geometry":{"type":"Point","coordinates":[-2.971200942993164,53.40506765343666]]}}
