var point = {"type":"FeatureCollection","features":[{"type":"Feature","properties":{"marker-color":"#ff0000","marker-size":"medium","marker-symbol":"college","name":"university of Liverpool"},"geometry":{"type":"Point","coordinates":[-2.9663515090942383,53.40733179031648]}},{"type":"Feature","properties":{"marker-color":"#ff0000","marker-size":"medium","marker-symbol":"college","name":"John University, Liverpool"},"geometry":{"type":"Point","coordinates":[-2.9717588424682617,53.40318717697404]}}]}